setup.py
flask_robohash/__init__.py
flask_robohash.egg-info/PKG-INFO
flask_robohash.egg-info/SOURCES.txt
flask_robohash.egg-info/dependency_links.txt
flask_robohash.egg-info/requires.txt
flask_robohash.egg-info/top_level.txt
flask_robohash.egg-info/zip-safe