Metadata-Version: 1.1
Name: flask-robohash
Version: 1.0
Summary: robohash.org avatars that you can use with the microframework Flask.
Home-page: https://github.com/syndbg/flask-robohash
Author: Anton Antonov
Author-email: anton.synd.antonov@gmail.com
License: MIT
Download-URL: https://github.com/syndbg/flask-robohash/archive/master.zip
Keywords: flask robo robohash.org hash robohash avatars robots monsters microframework
Platform: any
Classifier: Development Status :: 5 - Production/Stable
Classifier: Intended Audience :: Developers
Classifier: License :: OSI Approved :: MIT License
Classifier: Operating System :: OS Independent
Classifier: Programming Language :: Python :: 2
Classifier: Programming Language :: Python :: 2.7
Classifier: Programming Language :: Python :: 3
Classifier: Programming Language :: Python :: 3
Classifier: Programming Language :: Python :: 3.2
Classifier: Programming Language :: Python :: 3.3
Classifier: Programming Language :: Python
Classifier: Topic :: Internet :: WWW/HTTP :: Browsers
Classifier: Topic :: Internet :: WWW/HTTP :: Dynamic Content
Classifier: Topic :: Internet :: WWW/HTTP
Classifier: Topic :: Software Development :: Libraries :: Python Modules
Classifier: Topic :: Utilities
